pydon/__init__.py
pydon-0.1.0.dist-info/DESCRIPTION.rst
pydon-0.1.0.dist-info/METADATA
pydon-0.1.0.dist-info/RECORD
pydon-0.1.0.dist-info/WHEEL
pydon-0.1.0.dist-info/metadata.json
pydon-0.1.0.dist-info/top_level.txt
tests/__init__.py
tests/conftest.py
tests/test_pydon.py
