Metadata-Version: 2.0
Name: pydon
Version: 0.1.0
Summary: python data object notation. like json, but pythonic
Home-page: UNKNOWN
Author: Tucker Beck
Author-email: tucker.beck@gmail.com
License: MIT
Platform: UNKNOWN
Classifier: Development Status :: 3 - Alpha
Classifier: Intended Audience :: Developers
Classifier: Topic :: Software Development :: Libraries :: Python Modules
Classifier: License :: OSI Approved :: MIT License
Classifier: Programming Language :: Python :: 3
Classifier: Programming Language :: Python :: 3.3
Classifier: Programming Language :: Python :: 3.4
Classifier: Programming Language :: Python :: 3.5
Requires-Dist: pprintpp
Requires-Dist: py-buzz
Provides-Extra: dev
Requires-Dist: pytest-capturelog; extra == 'dev'
Requires-Dist: flake8; extra == 'dev'
Requires-Dist: pytest; extra == 'dev'
